{
    "geocode": {
        "time": 7.485238075256348,
        "optimal": true,
        "obj": 224.0,
        "sol": [
            [
                0
            ],
            [
                9
            ],
            [
                5
            ],
            [
                1
            ],
            [
                8
            ],
            [
                12
            ],
            [
                4
            ],
            [
                7,
                3
            ],
            [
                10
            ],
            [
                2
            ]
        ]
    }
}
